[
  {
    "imdbID": "tt39673634",
    "Title": "Sandiwara",
    "Year": 2026,
    "Rating10": 5.9,
    "Review": "Que fome. Super viajaria pra Malásia só pela culinária. Novos sabores, novas experiencias...\n\nE esse curta bate bem nessa tecla, com um pedacinho da cultura local. Historia, historia mesmo não tem. O que é uma pena, pois com uma direção tão boa e um conceito tão legal dava para ter feito algo mais completo do que apenas 10 minutinhos de filme.\n\nMichelle Yeoh tá ótima em alguns papéis. Já em outros, como a de influencer achei ela um pouquinho desconfortável e acabou caindo para o caricato.",
    "SafeForParents": true,
    "ForKids": false,
    "Watches": [
      "2026-07-13"
    ]
  }
]